duster/__init__.py
duster/duster.py
dustydata-0.0.7.dist-info/LICENSE.md
dustydata-0.0.7.dist-info/METADATA
dustydata-0.0.7.dist-info/WHEEL
dustydata-0.0.7.dist-info/top_level.txt
dustydata-0.0.7.dist-info/RECORD
